README.md
setup.py
abreai/__init__.py
abreai/shortener.py
abreai.egg-info/PKG-INFO
abreai.egg-info/SOURCES.txt
abreai.egg-info/dependency_links.txt
abreai.egg-info/requires.txt
abreai.egg-info/top_level.txt
abreai/models/data.py
abreai/models/url_info.py
abreai/models/data.py
abreai/models/url_info.py