Metadata-Version: 2.1
Name: abreai
Version: 1.0.1
Summary: A Wrapper to communicate with the https://abre.ai API
Author: Marcuth
Author-email: marcuth2006@gmail.com
License: MIT License
Keywords: abreai wrapper api
